{
  "game_id": "0022401106",
  "players": [
    {
      "player_id": 1630573,
      "player_name": "Sam Hauser",
      "team_abbreviation": "BOS",
      "jersey_num": "30",
      "starter": true,
      "min": 25.63,
      "pts": 6,
      "reb": 3,
      "oreb": 1,
      "dreb": 2,
      "ast": 0,
      "stl": 0,
      "blk": 0,
      "tov": 0,
      "fgm": 2,
      "fga": 5,
      "fg3m": 2,
      "fg3a": 5,
      "ftm": 0,
      "fta": 0,
      "pf": 4,
      "plus_minus": -12
    },
    {
      "player_id": 1628369,
      "player_name": "Jayson Tatum",
      "team_abbreviation": "BOS",
      "jersey_num": "0",
      "starter": true,
      "min": 31.88,
      "pts": 16,
      "reb": 3,
      "oreb": 0,
      "dreb": 3,
      "ast": 7,
      "stl": 1,
      "blk": 0,
      "tov": 2,
      "fgm": 4,
      "fga": 17,
      "fg3m": 2,
      "fg3a": 9,
      "ftm": 6,
      "fta": 7,
      "pf": 3,
      "plus_minus": -11
    },
    {
      "player_id": 1628436,
      "player_name": "Luke Kornet",
      "team_abbreviation": "BOS",
      "jersey_num": "40",
      "starter": true,
      "min": 21.48,
      "pts": 14,
      "reb": 6,
      "oreb": 6,
      "dreb": 0,
      "ast": 2,
      "stl": 0,
      "blk": 0,
      "tov": 0,
      "fgm": 7,
      "fga": 9,
      "fg3m": 0,
      "fg3a": 0,
      "ftm": 0,
      "fta": 0,
      "pf": 3,
      "plus_minus": 3
    },
    {
      "player_id": 1627759,
      "player_name": "Jaylen Brown",
      "team_abbreviation": "BOS",
      "jersey_num": "7",
      "starter": true,
      "min": 28.78,
      "pts": 24,
      "reb": 9,
      "oreb": 2,
      "dreb": 7,
      "ast": 4,
      "stl": 0,
      "blk": 0,
      "tov": 3,
      "fgm": 10,
      "fga": 20,
      "fg3m": 2,
      "fg3a": 6,
      "ftm": 2,
      "fta": 3,
      "pf": 2,
      "plus_minus": -1
    },
    {
      "player_id": 1628401,
      "player_name": "Derrick White",
      "team_abbreviation": "BOS",
      "jersey_num": "9",
      "starter": true,
      "min": 31.12,
      "pts": 16,
      "reb": 4,
      "oreb": 2,
      "dreb": 2,
      "ast": 6,
      "stl": 1,
      "blk": 2,
      "tov": 4,
      "fgm": 5,
      "fga": 11,
      "fg3m": 2,
      "fg3a": 7,
      "ftm": 4,
      "fta": 5,
      "pf": 0,
      "plus_minus": -13
    },
    {
      "player_id": 1630202,
      "player_name": "Payton Pritchard",
      "team_abbreviation": "BOS",
      "jersey_num": "11",
      "starter": true,
      "min": 31.28,
      "pts": 10,
      "reb": 4,
      "oreb": 2,
      "dreb": 2,
      "ast": 2,
      "stl": 0,
      "blk": 1,
      "tov": 1,
      "fgm": 4,
      "fga": 9,
      "fg3m": 2,
      "fg3a": 6,
      "ftm": 0,
      "fta": 0,
      "pf": 0,
      "plus_minus": -7
    },
    {
      "player_id": 1628470,
      "player_name": "Torrey Craig",
      "team_abbreviation": "BOS",
      "jersey_num": "12",
      "starter": true,
      "min": 19.08,
      "pts": 2,
      "reb": 3,
      "oreb": 2,
      "dreb": 1,
      "ast": 0,
      "stl": 0,
      "blk": 1,
      "tov": 0,
      "fgm": 1,
      "fga": 5,
      "fg3m": 0,
      "fg3a": 3,
      "ftm": 0,
      "fta": 0,
      "pf": 2,
      "plus_minus": -23
    },
    {
      "player_id": 1631248,
      "player_name": "Baylor Scheierman",
      "team_abbreviation": "BOS",
      "jersey_num": "55",
      "starter": true,
      "min": 16.88,
      "pts": 3,
      "reb": 3,
      "oreb": 2,
      "dreb": 1,
      "ast": 0,
      "stl": 1,
      "blk": 0,
      "tov": 0,
      "fgm": 1,
      "fga": 3,
      "fg3m": 1,
      "fg3a": 3,
      "ftm": 0,
      "fta": 0,
      "pf": 0,
      "plus_minus": -8
    },
    {
      "player_id": 1629674,
      "player_name": "Neemias Queta",
      "team_abbreviation": "BOS",
      "jersey_num": "88",
      "starter": true,
      "min": 18.75,
      "pts": 7,
      "reb": 7,
      "oreb": 2,
      "dreb": 5,
      "ast": 2,
      "stl": 0,
      "blk": 1,
      "tov": 0,
      "fgm": 3,
      "fga": 3,
      "fg3m": 0,
      "fg3a": 0,
      "ftm": 1,
      "fta": 1,
      "pf": 2,
      "plus_minus": -15
    },
    {
      "player_id": 1641809,
      "player_name": "Drew Peterson",
      "team_abbreviation": "BOS",
      "jersey_num": "13",
      "starter": true,
      "min": 5.03,
      "pts": 3,
      "reb": 0,
      "oreb": 0,
      "dreb": 0,
      "ast": 0,
      "stl": 0,
      "blk": 0,
      "tov": 0,
      "fgm": 1,
      "fga": 2,
      "fg3m": 1,
      "fg3a": 2,
      "ftm": 0,
      "fta": 0,
      "pf": 1,
      "plus_minus": -6
    },
    {
      "player_id": 1631120,
      "player_name": "JD Davison",
      "team_abbreviation": "BOS",
      "jersey_num": "20",
      "starter": true,
      "min": 5.03,
      "pts": 2,
      "reb": 1,
      "oreb": 0,
      "dreb": 1,
      "ast": 1,
      "stl": 0,
      "blk": 1,
      "tov": 2,
      "fgm": 1,
      "fga": 2,
      "fg3m": 0,
      "fg3a": 1,
      "ftm": 0,
      "fta": 0,
      "pf": 0,
      "plus_minus": -6
    },
    {
      "player_id": 1641775,
      "player_name": "Jordan Walsh",
      "team_abbreviation": "BOS",
      "jersey_num": "27",
      "starter": true,
      "min": 5.03,
      "pts": 0,
      "reb": 0,
      "oreb": 0,
      "dreb": 0,
      "ast": 0,
      "stl": 0,
      "blk": 0,
      "tov": 1,
      "fgm": 0,
      "fga": 1,
      "fg3m": 0,
      "fg3a": 1,
      "ftm": 0,
      "fta": 0,
      "pf": 0,
      "plus_minus": -6
    },
    {
      "player_id": 1630214,
      "player_name": "Xavier Tillman",
      "team_abbreviation": "BOS",
      "jersey_num": "26",
      "starter": true,
      "min": 0.0,
      "pts": 0,
      "reb": 0,
      "oreb": 0,
      "dreb": 0,
      "ast": 0,
      "stl": 0,
      "blk": 0,
      "tov": 0,
      "fgm": 0,
      "fga": 0,
      "fg3m": 0,
      "fg3a": 0,
      "ftm": 0,
      "fta": 0,
      "pf": 0,
      "plus_minus": 0
    },
    {
      "player_id": 201950,
      "player_name": "Jrue Holiday",
      "team_abbreviation": "BOS",
      "jersey_num": "4",
      "starter": true,
      "min": 0.0,
      "pts": 0,
      "reb": 0,
      "oreb": 0,
      "dreb": 0,
      "ast": 0,
      "stl": 0,
      "blk": 0,
      "tov": 0,
      "fgm": 0,
      "fga": 0,
      "fg3m": 0,
      "fg3a": 0,
      "ftm": 0,
      "fta": 0,
      "pf": 0,
      "plus_minus": 0
    },
    {
      "player_id": 201143,
      "player_name": "Al Horford",
      "team_abbreviation": "BOS",
      "jersey_num": "42",
      "starter": true,
      "min": 0.0,
      "pts": 0,
      "reb": 0,
      "oreb": 0,
      "dreb": 0,
      "ast": 0,
      "stl": 0,
      "blk": 0,
      "tov": 0,
      "fgm": 0,
      "fga": 0,
      "fg3m": 0,
      "fg3a": 0,
      "ftm": 0,
      "fta": 0,
      "pf": 0,
      "plus_minus": 0
    },
    {
      "player_id": 1641936,
      "player_name": "Miles Norris",
      "team_abbreviation": "BOS",
      "jersey_num": "44",
      "starter": true,
      "min": 0.0,
      "pts": 0,
      "reb": 0,
      "oreb": 0,
      "dreb": 0,
      "ast": 0,
      "stl": 0,
      "blk": 0,
      "tov": 0,
      "fgm": 0,
      "fga": 0,
      "fg3m": 0,
      "fg3a": 0,
      "ftm": 0,
      "fta": 0,
      "pf": 0,
      "plus_minus": 0
    },
    {
      "player_id": 204001,
      "player_name": "Kristaps Porzi\u0146\u0123is",
      "team_abbreviation": "BOS",
      "jersey_num": "8",
      "starter": true,
      "min": 0.0,
      "pts": 0,
      "reb": 0,
      "oreb": 0,
      "dreb": 0,
      "ast": 0,
      "stl": 0,
      "blk": 0,
      "tov": 0,
      "fgm": 0,
      "fga": 0,
      "fg3m": 0,
      "fg3a": 0,
      "ftm": 0,
      "fta": 0,
      "pf": 0,
      "plus_minus": 0
    },
    {
      "player_id": 1641796,
      "player_name": "Pelle Larsson",
      "team_abbreviation": "MIA",
      "jersey_num": "9",
      "starter": true,
      "min": 30.23,
      "pts": 16,
      "reb": 4,
      "oreb": 3,
      "dreb": 1,
      "ast": 4,
      "stl": 1,
      "blk": 0,
      "tov": 1,
      "fgm": 4,
      "fga": 9,
      "fg3m": 2,
      "fg3a": 3,
      "ftm": 6,
      "fta": 7,
      "pf": 2,
      "plus_minus": 13
    },
    {
      "player_id": 1628389,
      "player_name": "Bam Adebayo",
      "team_abbreviation": "MIA",
      "jersey_num": "13",
      "starter": true,
      "min": 30.68,
      "pts": 21,
      "reb": 5,
      "oreb": 0,
      "dreb": 5,
      "ast": 6,
      "stl": 0,
      "blk": 0,
      "tov": 0,
      "fgm": 9,
      "fga": 15,
      "fg3m": 2,
      "fg3a": 3,
      "ftm": 1,
      "fta": 1,
      "pf": 2,
      "plus_minus": 13
    },
    {
      "player_id": 1642276,
      "player_name": "Kel'el Ware",
      "team_abbreviation": "MIA",
      "jersey_num": "7",
      "starter": true,
      "min": 31.98,
      "pts": 7,
      "reb": 5,
      "oreb": 2,
      "dreb": 3,
      "ast": 0,
      "stl": 1,
      "blk": 1,
      "tov": 0,
      "fgm": 2,
      "fga": 5,
      "fg3m": 0,
      "fg3a": 0,
      "ftm": 3,
      "fta": 4,
      "pf": 1,
      "plus_minus": 7
    },
    {
      "player_id": 202692,
      "player_name": "Alec Burks",
      "team_abbreviation": "MIA",
      "jersey_num": "18",
      "starter": true,
      "min": 19.2,
      "pts": 10,
      "reb": 2,
      "oreb": 0,
      "dreb": 2,
      "ast": 0,
      "stl": 0,
      "blk": 0,
      "tov": 0,
      "fgm": 4,
      "fga": 5,
      "fg3m": 1,
      "fg3a": 2,
      "ftm": 1,
      "fta": 1,
      "pf": 0,
      "plus_minus": -10
    },
    {
      "player_id": 1629639,
      "player_name": "Tyler Herro",
      "team_abbreviation": "MIA",
      "jersey_num": "14",
      "starter": true,
      "min": 38.02,
      "pts": 25,
      "reb": 6,
      "oreb": 1,
      "dreb": 5,
      "ast": 9,
      "stl": 2,
      "blk": 0,
      "tov": 0,
      "fgm": 7,
      "fga": 18,
      "fg3m": 2,
      "fg3a": 6,
      "ftm": 9,
      "fta": 10,
      "pf": 1,
      "plus_minus": 19
    },
    {
      "player_id": 1629312,
      "player_name": "Haywood Highsmith",
      "team_abbreviation": "MIA",
      "jersey_num": "24",
      "starter": true,
      "min": 25.83,
      "pts": 10,
      "reb": 4,
      "oreb": 2,
      "dreb": 2,
      "ast": 0,
      "stl": 0,
      "blk": 1,
      "tov": 0,
      "fgm": 4,
      "fga": 8,
      "fg3m": 2,
      "fg3a": 6,
      "ftm": 0,
      "fta": 0,
      "pf": 3,
      "plus_minus": 13
    },
    {
      "player_id": 1630558,
      "player_name": "Davion Mitchell",
      "team_abbreviation": "MIA",
      "jersey_num": "45",
      "starter": true,
      "min": 33.6,
      "pts": 13,
      "reb": 4,
      "oreb": 1,
      "dreb": 3,
      "ast": 7,
      "stl": 3,
      "blk": 0,
      "tov": 1,
      "fgm": 5,
      "fga": 10,
      "fg3m": 3,
      "fg3a": 6,
      "ftm": 0,
      "fta": 0,
      "pf": 3,
      "plus_minus": 21
    },
    {
      "player_id": 203937,
      "player_name": "Kyle Anderson",
      "team_abbreviation": "MIA",
      "jersey_num": "20",
      "starter": true,
      "min": 23.78,
      "pts": 19,
      "reb": 1,
      "oreb": 1,
      "dreb": 0,
      "ast": 1,
      "stl": 1,
      "blk": 0,
      "tov": 1,
      "fgm": 7,
      "fga": 11,
      "fg3m": 1,
      "fg3a": 2,
      "ftm": 4,
      "fta": 4,
      "pf": 0,
      "plus_minus": 17
    },
    {
      "player_id": 1641815,
      "player_name": "Isaiah Stevens",
      "team_abbreviation": "MIA",
      "jersey_num": "4",
      "starter": true,
      "min": 1.67,
      "pts": 0,
      "reb": 2,
      "oreb": 0,
      "dreb": 2,
      "ast": 0,
      "stl": 0,
      "blk": 0,
      "tov": 0,
      "fgm": 0,
      "fga": 1,
      "fg3m": 0,
      "fg3a": 1,
      "ftm": 0,
      "fta": 0,
      "pf": 0,
      "plus_minus": 3
    },
    {
      "player_id": 1630528,
      "player_name": "Josh Christopher",
      "team_abbreviation": "MIA",
      "jersey_num": "8",
      "starter": true,
      "min": 1.67,
      "pts": 3,
      "reb": 0,
      "oreb": 0,
      "dreb": 0,
      "ast": 0,
      "stl": 0,
      "blk": 0,
      "tov": 1,
      "fgm": 1,
      "fga": 1,
      "fg3m": 1,
      "fg3a": 1,
      "ftm": 0,
      "fta": 0,
      "pf": 1,
      "plus_minus": 3
    },
    {
      "player_id": 1631170,
      "player_name": "Jaime Jaquez Jr.",
      "team_abbreviation": "MIA",
      "jersey_num": "11",
      "starter": true,
      "min": 1.67,
      "pts": 0,
      "reb": 1,
      "oreb": 1,
      "dreb": 0,
      "ast": 1,
      "stl": 0,
      "blk": 0,
      "tov": 0,
      "fgm": 0,
      "fga": 0,
      "fg3m": 0,
      "fg3a": 0,
      "ftm": 0,
      "fta": 0,
      "pf": 0,
      "plus_minus": 3
    },
    {
      "player_id": 1642352,
      "player_name": "Keshad Johnson",
      "team_abbreviation": "MIA",
      "jersey_num": "16",
      "starter": true,
      "min": 1.67,
      "pts": 0,
      "reb": 0,
      "oreb": 0,
      "dreb": 0,
      "ast": 0,
      "stl": 1,
      "blk": 0,
      "tov": 0,
      "fgm": 0,
      "fga": 0,
      "fg3m": 0,
      "fg3a": 0,
      "ftm": 0,
      "fta": 0,
      "pf": 0,
      "plus_minus": 3
    },
    {
      "player_id": 1626179,
      "player_name": "Terry Rozier",
      "team_abbreviation": "MIA",
      "jersey_num": "2",
      "starter": true,
      "min": 0.0,
      "pts": 0,
      "reb": 0,
      "oreb": 0,
      "dreb": 0,
      "ast": 0,
      "stl": 0,
      "blk": 0,
      "tov": 0,
      "fgm": 0,
      "fga": 0,
      "fg3m": 0,
      "fg3a": 0,
      "ftm": 0,
      "fta": 0,
      "pf": 0,
      "plus_minus": 0
    },
    {
      "player_id": 1631107,
      "player_name": "Nikola Jovi\u0107",
      "team_abbreviation": "MIA",
      "jersey_num": "5",
      "starter": true,
      "min": 0.0,
      "pts": 0,
      "reb": 0,
      "oreb": 0,
      "dreb": 0,
      "ast": 0,
      "stl": 0,
      "blk": 0,
      "tov": 0,
      "fgm": 0,
      "fga": 0,
      "fg3m": 0,
      "fg3a": 0,
      "ftm": 0,
      "fta": 0,
      "pf": 0,
      "plus_minus": 0
    },
    {
      "player_id": 201567,
      "player_name": "Kevin Love",
      "team_abbreviation": "MIA",
      "jersey_num": "42",
      "starter": true,
      "min": 0.0,
      "pts": 0,
      "reb": 0,
      "oreb": 0,
      "dreb": 0,
      "ast": 0,
      "stl": 0,
      "blk": 0,
      "tov": 0,
      "fgm": 0,
      "fga": 0,
      "fg3m": 0,
      "fg3a": 0,
      "ftm": 0,
      "fta": 0,
      "pf": 0,
      "plus_minus": 0
    },
    {
      "player_id": 1629130,
      "player_name": "Duncan Robinson",
      "team_abbreviation": "MIA",
      "jersey_num": "55",
      "starter": true,
      "min": 0.0,
      "pts": 0,
      "reb": 0,
      "oreb": 0,
      "dreb": 0,
      "ast": 0,
      "stl": 0,
      "blk": 0,
      "tov": 0,
      "fgm": 0,
      "fga": 0,
      "fg3m": 0,
      "fg3a": 0,
      "ftm": 0,
      "fta": 0,
      "pf": 0,
      "plus_minus": 0
    },
    {
      "player_id": 1630696,
      "player_name": "Dru Smith",
      "team_abbreviation": "MIA",
      "jersey_num": "12",
      "starter": true,
      "min": 0.0,
      "pts": 0,
      "reb": 0,
      "oreb": 0,
      "dreb": 0,
      "ast": 0,
      "stl": 0,
      "blk": 0,
      "tov": 0,
      "fgm": 0,
      "fga": 0,
      "fg3m": 0,
      "fg3a": 0,
      "ftm": 0,
      "fta": 0,
      "pf": 0,
      "plus_minus": 0
    },
    {
      "player_id": 203952,
      "player_name": "Andrew Wiggins",
      "team_abbreviation": "MIA",
      "jersey_num": "22",
      "starter": true,
      "min": 0.0,
      "pts": 0,
      "reb": 0,
      "oreb": 0,
      "dreb": 0,
      "ast": 0,
      "stl": 0,
      "blk": 0,
      "tov": 0,
      "fgm": 0,
      "fga": 0,
      "fg3m": 0,
      "fg3a": 0,
      "ftm": 0,
      "fta": 0,
      "pf": 0,
      "plus_minus": 0
    }
  ],
  "home_team": "BOS",
  "away_team": "MIA",
  "home_score": 103,
  "away_score": 124,
  "total_players": 35,
  "total_fga": 170
}